limepkg_scrive/__init__.py
limepkg_scrive/config/__init__.py
limepkg_scrive/config/schema.py
limepkg_scrive/translations/__init__.py
limepkg_scrive/translations/da.po
limepkg_scrive/translations/de.po
limepkg_scrive/translations/en.po
limepkg_scrive/translations/fi.po
limepkg_scrive/translations/nl.po
limepkg_scrive/translations/no.po
limepkg_scrive/translations/sv.po
limepkg_scrive/web_components/__init__.py
limepkg_scrive/web_components/static/cjs/index-c74a2cd5.js
limepkg_scrive/web_components/static/cjs/index.cjs.js
limepkg_scrive/web_components/static/cjs/limepkg-scrive-lwc-components.cjs.js
limepkg_scrive/web_components/static/cjs/loader.cjs.js
limepkg_scrive/web_components/static/cjs/lwc-limepkg-scrive-loader.cjs.entry.js
limepkg_scrive/web_components/static/cjs/lwc-limepkg-scrive-main.cjs.entry.js
limepkg_scrive/web_components/static/cjs/types-f1bea775.js
limepkg_scrive/web_components/static/collection/collection-manifest.json
limepkg_scrive/web_components/static/collection/commands/esign/esign.command.js
limepkg_scrive/web_components/static/collection/commands/esign/esign.handler.js
limepkg_scrive/web_components/static/collection/components/lwc-limepkg-scrive-loader/lwc-limepkg-scrive-loader.js
limepkg_scrive/web_components/static/collection/components/lwc-limepkg-scrive-main/lwc-limepkg-scrive-main.css
limepkg_scrive/web_components/static/collection/components/lwc-limepkg-scrive-main/lwc-limepkg-scrive-main.js
limepkg_scrive/web_components/static/collection/lime-web-component-platform.browser.js
limepkg_scrive/web_components/static/collection/types.js
limepkg_scrive/web_components/static/esm/index-e7f7b2d6.js
limepkg_scrive/web_components/static/esm/index.js
limepkg_scrive/web_components/static/esm/limepkg-scrive-lwc-components.js
limepkg_scrive/web_components/static/esm/loader.js
limepkg_scrive/web_components/static/esm/lwc-limepkg-scrive-loader.entry.js
limepkg_scrive/web_components/static/esm/lwc-limepkg-scrive-main.entry.js
limepkg_scrive-3.0.0.dist-info/entry_points.txt
limepkg_scrive-3.0.0.dist-info/WHEEL
limepkg_scrive-3.0.0.dist-info/METADATA
limepkg_scrive-3.0.0.dist-info/RECORD
