Metadata-Version: 2.1
Name: limepkg-scrive
Version: 3.0.0
Summary: Lime CRM package
Author: Author
Author-email: author@lime.tech
Requires-Python: >=3.11,<4.0
Classifier: Programming Language :: Python :: 3
Classifier: Programming Language :: Python :: 3.11
Requires-Dist: lime-crm (>=2.526.0,<3.0.0)
